Workbook

Sheet README
A1: Instructions
B2: This spreadsheet is step 4 of the simplified risk assessment. However it is modified to make the data entry faster for you. You should do the following: 1. Enter all of your assets in the "Assets" sheet. Select the AssetType from the drop-down list and type in the Asset name. 2. In the "Vulnerabilities" sheet, enter the Threat number, Asset number and Vulnerability number, then type in the description of the vulnerability. 3. Check the coverage of threats for each asset by looking at the summary in the "TVAMatrix" sheet. IMPORTANT: the "TVAMatrix" sheet is auto-generated; you do NOT edit it. But you should use it as a check to make sure you haven't missed any TVAs. 4. Once you are confident all TVAs are in the "Vulnerabilities" sheet, allocate a Likelihood and Impact to each. Select from the drop-down boxes. The Risk is auto-generated. 5. Finally, manually enter Rank for each TVA.
A5: Limits | B5: Some parts of the sheets are formatted for a limited number of values. In most cases, you do not need to worry about the limits - they should be sufficient in simple cases. The limits are: - Maximum of 100 assets. (This could be increased by expanding the "Assets" sheet down into further rows, and similar for the "TVAMatrix"). - Four (4) vulnerabilities per T/A pair supported in the TVAMatrix. That is, T1V1A1, T1V2A1, T1V3A1, T1V4A1 are allowed and will appear in the TVAMatrix automatically. However while T1V5A1 can be added to the Vulnerabilities sheet, it will not appear in the TVAMatrix. (If a specific T/A pair needed more than 4 vulnerabilities, then rows could be inserted into the TVAMatrix and formula from the above row copied down.)

Sheet Assets
A1: AssetNum | B1: AssetType | C1: Asset
A2: 1 | B2: Data | C2: Client financial records (tax returns, financial statements)
A3: 2 | B3: Data | C3: Client personal information (names, TFNs, addresses)
A4: 3 | B4: Data | C4: Business financial data (accounts, payroll, invoices)
A5: 4 | B5: Data | C5: Staff credentials and authentication data
A6: 5 | B6: Hardware | C6: OpenWRT router/firewall (primary network device)
A7: 6 | B7: Hardware | C7: Staff Windows workstations (x8)
A8: 7 | B8: Hardware | C8: File server (stores client and business records)
A9: 8 | B9: Hardware | C9: Network switches and cabling
A10: 9 | B10: Software | C10: OpenWRT firmware and firewall software
A11: 10 | B11: Software | C11: Windows 10 OS on staff workstations
A12: 11 | B12: Software | C12: Accounting software (client data processing)
A13: 12 | B13: People | C13: IT support officer
... A15: 14 | B15: People | C15: Accountants (x5)

Sheet Vulnerabilities
A1: ThreatNum | B1: Threat | C1: AssetNum | D1: AssetType | E1: Asset | F1: VulnNum | G1: TVA | H1: Vulnerability | I1: Likelihood | J1: Impact | K1: Risk | L1: Rank
A2: 1 | B2: People errors | C2: 1 | D2: Data | E2: Client financial records (tax returns, financial statements) | F2: 1 | G2: T1V1A1 | H2: Staff emails client financial records to wrong recipient without encryption | I2: Moderate | J2: High | L2: 3
A3: 1 | B3: People errors | C3: 2 | D3: Data | E3: Client personal information (names, TFNs, addresses) | F3: 1 | G3: T1V1A2 | H3: Accountant accidently shares client personal info in unencrypted email attachment | I3: Moderate | J3: High | L3: 4
A4: 1 | B4: People errors | C4: 6 | D4: Hardware | E4: Staff Windows workstations (x8) | F4: 1 | G4: T1V1A6 | H4: Staff member accidentally deletes critical client folder on file server | I4: Low | J4: High | L4: 6
A5: 1 | B5: People errors | C5: 13 | D5: People | E5: Administrative staff (x2) | F5: 1 | G5: T1V1A13 | H5: Admin staff clicks phishing link due to lack of security awareness training | I5: Moderate | J5: Moderate | L5: 7
A6: 2 | B6: Software attacks | C6: 1 | D6: Data | E6: Client financial records (tax returns, financial statements) | F6: 1 | G6: T2V1A1 | H6: Ransomware encrypts client financial records via unpatched workstation vulnerability | I6: Moderate | J6: High | L6: 1
A7: 2 | B7: Software attacks | C7: 4 | D7: Data | E7: Staff credentials and authentication data | F7: 1 | G7: T2V1A4 | H7: Brute-force attack on SSH (port 22) compromises router admin credentials | I7: Moderate | J7: High | L7: 2
A8: 2 | B8: Software attacks | C8: 9 | D8: Software | E8: OpenWRT firmware and firewall software | F8: 1 | G8: T2V1A9 | H8: OpenWRT firmware contains unpatched CVE exploited remotely via WAN interface | I8: Low | J8: High | L8: 5
A9: 2 | B9: Software attacks | C9: 10 | D9: Software | E9: Windows 10 OS on staff workstations | F9: 1 | G9: T2V1A10 | H9: Malware installed on Windows workstation via malicious email attachment | I9: Moderate | J9: Moderate | L9: 8
A10: 3 | B10: Information extortion | C10: 1 | D10: Data | E10: Client financial records (tax returns, financial statements) | F10: 1 | G10: T3V1A1 | H10: Attacker steals encrypted client tax records and demands ransom to prevent release | I10: Low | J10: High | L10: 9
A11: 3 | B11: Information extortion | C11: 2 | D11: Data | E11: Client personal information (names, TFNs, addresses) | F11: 1 | G11: T3V1A2 | H11: Client personal data (TFNs) stolen and used as leverage in extortion demand | I11: Low | J11: High | L11: 10
A12: 4 | B12: Espionage and trespass | C12: 1 | D12: Data | E12: Client financial records (tax returns, financial statements) | F12: 1 | G12: T4V1A1 | H12: Competitor gains unauthorised access to client financial records via network intrusion | I12: Low | J12: High | L12: 11
A13: 4 | B13: Espionage and trespass | C13: 4 | D13: Data | E13: Staff credentials and authentication data | F13: 1 | G13: T4V1A4 | H13: Attacker intercepts HTTP traffic to capture staff login credentials in plaintext | I13: Moderate | J13: High | L13: 12
... A23: 12 | B23: IP compromises | C23: 1 | D23: Data | E23: Client financial records (tax returns, financial statements) | F23: 1 | G23: T12V1A1 | H23: Client financial data published online breaching Australian Privacy Act obligations | I23: Low | J23: High | L23: 22
B101: =_xlfn.IFNA(VLOOKUP(A101,InfoSecThreats!A:B,2,FALSE()),"") | D101: =_xlfn.IFNA(VLOOKUP(Vulnerabilities!C101,Assets!A:C,2,FALSE()),"") | E101: =_xlfn.IFNA(VLOOKUP(Vulnerabilities!C101,Assets!A:C,3,FALSE()),"") | G101: =IF(ISBLANK(F101),"",_xlfn.CONCAT("T",A101,"V",F101,"A",C101)) | K101: =_xlfn.IFNA(VLOOKUP(_xlfn.CONCAT(I101,"|",J101),RiskValues!C:D,2,FALSE()),"")
B102: =_xlfn.IFNA(VLOOKUP(A102,InfoSecThreats!A:B,2,FALSE()),"") | D102: =_xlfn.IFNA(VLOOKUP(Vulnerabilities!C102,Assets!A:C,2,FALSE()),"") | E102: =_xlfn.IFNA(VLOOKUP(Vulnerabilities!C102,Assets!A:C,3,FALSE()),"") | G102: =IF(ISBLANK(F102),"",_xlfn.CONCAT("T",A102,"V",F102,"A",C102)) | K102: =_xlfn.IFNA(VLOOKUP(_xlfn.CONCAT(I102,"|",J102),RiskValues!C:D,2,FALSE()),"")
B103: =_xlfn.IFNA(VLOOKUP(A103,InfoSecThreats!A:B,2,FALSE()),"") | D103: =_xlfn.IFNA(VLOOKUP(Vulnerabilities!C103,Assets!A:C,2,FALSE()),"") | E103: =_xlfn.IFNA(VLOOKUP(Vulnerabilities!C103,Assets!A:C,3,FALSE()),"") | G103: =IF(ISBLANK(F103),"",_xlfn.CONCAT("T",A103,"V",F103,"A",C103)) | K103: =_xlfn.IFNA(VLOOKUP(_xlfn.CONCAT(I103,"|",J103),RiskValues!C:D,2,FALSE()),"")
B104: =_xlfn.IFNA(VLOOKUP(A104,InfoSecThreats!A:B,2,FALSE()),"") | D104: =_xlfn.IFNA(VLOOKUP(Vulnerabilities!C104,Assets!A:C,2,FALSE()),"") | E104: =_xlfn.IFNA(VLOOKUP(Vulnerabilities!C104,Assets!A:C,3,FALSE()),"") | G104: =IF(ISBLANK(F104),"",_xlfn.CONCAT("T",A104,"V",F104,"A",C104)) | K104: =_xlfn.IFNA(VLOOKUP(_xlfn.CONCAT(I104,"|",J104),RiskValues!C:D,2,FALSE()),"")
B105: =_xlfn.IFNA(VLOOKUP(A105,InfoSecThreats!A:B,2,FALSE()),"") | D105: =_xlfn.IFNA(VLOOKUP(Vulnerabilities!C105,Assets!A:C,2,FALSE()),"") | E105: =_xlfn.IFNA(VLOOKUP(Vulnerabilities!C105,Assets!A:C,3,FALSE()),"") | G105: =IF(ISBLANK(F105),"",_xlfn.CONCAT("T",A105,"V",F105,"A",C105)) | K105: =_xlfn.IFNA(VLOOKUP(_xlfn.CONCAT(I105,"|",J105),RiskValues!C:D,2,FALSE()),"")
B106: =_xlfn.IFNA(VLOOKUP(A106,InfoSecThreats!A:B,2,FALSE()),"") | D106: =_xlfn.IFNA(VLOOKUP(Vulnerabilities!C106,Assets!A:C,2,FALSE()),"") | E106: =_xlfn.IFNA(VLOOKUP(Vulnerabilities!C106,Assets!A:C,3,FALSE()),"") | G106: =IF(ISBLANK(F106),"",_xlfn.CONCAT("T",A106,"V",F106,"A",C106)) | K106: =_xlfn.IFNA(VLOOKUP(_xlfn.CONCAT(I106,"|",J106),RiskValues!C:D,2,FALSE()),"")
B107: =_xlfn.IFNA(VLOOKUP(A107,InfoSecThreats!A:B,2,FALSE()),"") | D107: =_xlfn.IFNA(VLOOKUP(Vulnerabilities!C107,Assets!A:C,2,FALSE()),"") | E107: =_xlfn.IFNA(VLOOKUP(Vulnerabilities!C107,Assets!A:C,3,FALSE()),"") | G107: =IF(ISBLANK(F107),"",_xlfn.CONCAT("T",A107,"V",F107,"A",C107)) | K107: =_xlfn.IFNA(VLOOKUP(_xlfn.CONCAT(I107,"|",J107),RiskValues!C:D,2,FALSE()),"")
B108: =_xlfn.IFNA(VLOOKUP(A108,InfoSecThreats!A:B,2,FALSE()),"") | D108: =_xlfn.IFNA(VLOOKUP(Vulnerabilities!C108,Assets!A:C,2,FALSE()),"") | E108: =_xlfn.IFNA(VLOOKUP(Vulnerabilities!C108,Assets!A:C,3,FALSE()),"") | G108: =IF(ISBLANK(F108),"",_xlfn.CONCAT("T",A108,"V",F108,"A",C108)) | K108: =_xlfn.IFNA(VLOOKUP(_xlfn.CONCAT(I108,"|",J108),RiskValues!C:D,2,FALSE()),"")
B109: =_xlfn.IFNA(VLOOKUP(A109,InfoSecThreats!A:B,2,FALSE()),"") | D109: =_xlfn.IFNA(VLOOKUP(Vulnerabilities!C109,Assets!A:C,2,FALSE()),"") | E109: =_xlfn.IFNA(VLOOKUP(Vulnerabilities!C109,Assets!A:C,3,FALSE()),"") | G109: =IF(ISBLANK(F109),"",_xlfn.CONCAT("T",A109,"V",F109,"A",C109)) | K109: =_xlfn.IFNA(VLOOKUP(_xlfn.CONCAT(I109,"|",J109),RiskValues!C:D,2,FALSE()),"")
B110: =_xlfn.IFNA(VLOOKUP(A110,InfoSecThreats!A:B,2,FALSE()),"") | D110: =_xlfn.IFNA(VLOOKUP(Vulnerabilities!C110,Assets!A:C,2,FALSE()),"") | E110: =_xlfn.IFNA(VLOOKUP(Vulnerabilities!C110,Assets!A:C,3,FALSE()),"") | G110: =IF(ISBLANK(F110),"",_xlfn.CONCAT("T",A110,"V",F110,"A",C110)) | K110: =_xlfn.IFNA(VLOOKUP(_xlfn.CONCAT(I110,"|",J110),RiskValues!C:D,2,FALSE()),"")
B111: =_xlfn.IFNA(VLOOKUP(A111,InfoSecThreats!A:B,2,FALSE()),"") | D111: =_xlfn.IFNA(VLOOKUP(Vulnerabilities!C111,Assets!A:C,2,FALSE()),"") | E111: =_xlfn.IFNA(VLOOKUP(Vulnerabilities!C111,Assets!A:C,3,FALSE()),"") | G111: =IF(ISBLANK(F111),"",_xlfn.CONCAT("T",A111,"V",F111,"A",C111)) | K111: =_xlfn.IFNA(VLOOKUP(_xlfn.CONCAT(I111,"|",J111),RiskValues!C:D,2,FALSE()),"")
B112: =_xlfn.IFNA(VLOOKUP(A112,InfoSecThreats!A:B,2,FALSE()),"") | D112: =_xlfn.IFNA(VLOOKUP(Vulnerabilities!C112,Assets!A:C,2,FALSE()),"") | E112: =_xlfn.IFNA(VLOOKUP(Vulnerabilities!C112,Assets!A:C,3,FALSE()),"") | G112: =IF(ISBLANK(F112),"",_xlfn.CONCAT("T",A112,"V",F112,"A",C112)) | K112: =_xlfn.IFNA(VLOOKUP(_xlfn.CONCAT(I112,"|",J112),RiskValues!C:D,2,FALSE()),"")
... B401: =_xlfn.IFNA(VLOOKUP(A401,InfoSecThreats!A:B,2,FALSE()),"") | D401: =_xlfn.IFNA(VLOOKUP(Vulnerabilities!C401,Assets!A:C,2,FALSE()),"") | E401: =_xlfn.IFNA(VLOOKUP(Vulnerabilities!C401,Assets!A:C,3,FALSE()),"") | G401: =IF(ISBLANK(F401),"",_xlfn.CONCAT("T",A401,"V",F401,"A",C401)) | K401: =_xlfn.IFNA(VLOOKUP(_xlfn.CONCAT(I401,"|",J401),RiskValues!C:D,2,FALSE()),"")

Sheet DO NOT EDIT --->
A1: Do not edit any of the following sheets:
A2: AssetTypes
A3: RiskValues
A4: InfoSecThreats
A6: TVAMAtrix | C6: (but you should look at the TVAMatrix sheet)

Sheet TVAMatrix
A1: AssetNum | B1: AssetType | C1: Asset | D1: VulnNum | E1: 1 | F1: 2 | G1: 3 | H1: 4 | I1: 5 | J1: 6 | K1: 7 | L1: 8 | M1: 9 | N1: 10 | O1: 11 | P1: 12
E2: =VLOOKUP(E1,InfoSecThreats!$A:$B,2,FALSE()) -> People errors | F2: =VLOOKUP(F1,InfoSecThreats!$A:$B,2,FALSE()) -> Software attacks | G2: =VLOOKUP(G1,InfoSecThreats!$A:$B,2,FALSE()) -> Information extortion | H2: =VLOOKUP(H1,InfoSecThreats!$A:$B,2,FALSE()) -> Espionage and trespass | I2: =VLOOKUP(I1,InfoSecThreats!$A:$B,2,FALSE()) -> Theft | J2: =VLOOKUP(J1,InfoSecThreats!$A:$B,2,FALSE()) -> Technological obsolescence | K2: =VLOOKUP(K1,InfoSecThreats!$A:$B,2,FALSE()) -> Forces of nature | L2: =VLOOKUP(L1,InfoSecThreats!$A:$B,2,FALSE()) -> Technical hardware failures or errors | ... P2: =VLOOKUP(P1,InfoSecThreats!$A:$B,2,FALSE()) -> IP compromises
A3: 1 | B3: =IF(VLOOKUP($A3,Assets!$A:$C,2,FALSE())=0,"",VLOOKUP($A3,Assets!$A:$C,2,FALSE())) -> Data | C3: =IF(VLOOKUP($A3,Assets!$A:$C,3,FALSE())=0,"",VLOOKUP($A3,Assets!$A:$C,3,FALSE())) -> Client financial records (tax returns, financial statements) | D3: 1 | E3: =_xlfn.IFNA(VLOOKUP(_xlfn.CONCAT("T",E$1,"V",$D3,"A",$A3),Vulnerabilities!$G:$G,1,FALSE()),"") -> T1V1A1 | F3: =_xlfn.IFNA(VLOOKUP(_xlfn.CONCAT("T",F$1,"V",$D3,"A",$A3),Vulnerabilities!$G:$G,1,FALSE()),"") -> T2V1A1 | G3: =_xlfn.IFNA(VLOOKUP(_xlfn.CONCAT("T",G$1,"V",$D3,"A",$A3),Vulnerabilities!$G:$G,1,FALSE()),"") -> T3V1A1 | H3: =_xlfn.IFNA(VLOOKUP(_xlfn.CONCAT("T",H$1,"V",$D3,"A",$A3),Vulnerabilities!$G:$G,1,FALSE()),"") -> T4V1A1 | I3: =_xlfn.IFNA(VLOOKUP(_xlfn.CONCAT("T",I$1,"V",$D3,"A",$A3),Vulnerabilities!$G:$G,1,FALSE()),"") | J3: =_xlfn.IFNA(VLOOKUP(_xlfn.CONCAT("T",J$1,"V",$D3,"A",$A3),Vulnerabilities!$G:$G,1,FALSE()),"") | K3: =_xlfn.IFNA(VLOOKUP(_xlfn.CONCAT("T",K$1,"V",$D3,"A",$A3),Vulnerabilities!$G:$G,1,FALSE()),"") | L3: =_xlfn.IFNA(VLOOKUP(_xlfn.CONCAT("T",L$1,"V",$D3,"A",$A3),Vulnerabilities!$G:$G,1,FALSE()),"") | ... P3: =_xlfn.IFNA(VLOOKUP(_xlfn.CONCAT("T",P$1,"V",$D3,"A",$A3),Vulnerabilities!$G:$G,1,FALSE()),"") -> T12V1A1
A4: 1 | B4: =IF(VLOOKUP($A4,Assets!$A:$C,2,FALSE())=0,"",VLOOKUP($A4,Assets!$A:$C,2,FALSE())) -> Data | C4: =IF(VLOOKUP($A4,Assets!$A:$C,3,FALSE())=0,"",VLOOKUP($A4,Assets!$A:$C,3,FALSE())) -> Client financial records (tax returns, financial statements) | D4: 2 | E4: =_xlfn.IFNA(VLOOKUP(_xlfn.CONCAT("T",E$1,"V",$D4,"A",$A4),Vulnerabilities!$G:$G,1,FALSE()),"") | F4: =_xlfn.IFNA(VLOOKUP(_xlfn.CONCAT("T",F$1,"V",$D4,"A",$A4),Vulnerabilities!$G:$G,1,FALSE()),"") | G4: =_xlfn.IFNA(VLOOKUP(_xlfn.CONCAT("T",G$1,"V",$D4,"A",$A4),Vulnerabilities!$G:$G,1,FALSE()),"") | H4: =_xlfn.IFNA(VLOOKUP(_xlfn.CONCAT("T",H$1,"V",$D4,"A",$A4),Vulnerabilities!$G:$G,1,FALSE()),"") | I4: =_xlfn.IFNA(VLOOKUP(_xlfn.CONCAT("T",I$1,"V",$D4,"A",$A4),Vulnerabilities!$G:$G,1,FALSE()),"") | J4: =_xlfn.IFNA(VLOOKUP(_xlfn.CONCAT("T",J$1,"V",$D4,"A",$A4),Vulnerabilities!$G:$G,1,FALSE()),"") | K4: =_xlfn.IFNA(VLOOKUP(_xlfn.CONCAT("T",K$1,"V",$D4,"A",$A4),Vulnerabilities!$G:$G,1,FALSE()),"") | L4: =_xlfn.IFNA(VLOOKUP(_xlfn.CONCAT("T",L$1,"V",$D4,"A",$A4),Vulnerabilities!$G:$G,1,FALSE()),"") | ... P4: =_xlfn.IFNA(VLOOKUP(_xlfn.CONCAT("T",P$1,"V",$D4,"A",$A4),Vulnerabilities!$G:$G,1,FALSE()),"")
A5: 1 | B5: =IF(VLOOKUP($A5,Assets!$A:$C,2,FALSE())=0,"",VLOOKUP($A5,Assets!$A:$C,2,FALSE())) -> Data | C5: =IF(VLOOKUP($A5,Assets!$A:$C,3,FALSE())=0,"",VLOOKUP($A5,Assets!$A:$C,3,FALSE())) -> Client financial records (tax returns, financial statements) | D5: 3 | E5: =_xlfn.IFNA(VLOOKUP(_xlfn.CONCAT("T",E$1,"V",$D5,"A",$A5),Vulnerabilities!$G:$G,1,FALSE()),"") | F5: =_xlfn.IFNA(VLOOKUP(_xlfn.CONCAT("T",F$1,"V",$D5,"A",$A5),Vulnerabilities!$G:$G,1,FALSE()),"") | G5: =_xlfn.IFNA(VLOOKUP(_xlfn.CONCAT("T",G$1,"V",$D5,"A",$A5),Vulnerabilities!$G:$G,1,FALSE()),"") | H5: =_xlfn.IFNA(VLOOKUP(_xlfn.CONCAT("T",H$1,"V",$D5,"A",$A5),Vulnerabilities!$G:$G,1,FALSE()),"") | I5: =_xlfn.IFNA(VLOOKUP(_xlfn.CONCAT("T",I$1,"V",$D5,"A",$A5),Vulnerabilities!$G:$G,1,FALSE()),"") | J5: =_xlfn.IFNA(VLOOKUP(_xlfn.CONCAT("T",J$1,"V",$D5,"A",$A5),Vulnerabilities!$G:$G,1,FALSE()),"") | K5: =_xlfn.IFNA(VLOOKUP(_xlfn.CONCAT("T",K$1,"V",$D5,"A",$A5),Vulnerabilities!$G:$G,1,FALSE()),"") | L5: =_xlfn.IFNA(VLOOKUP(_xlfn.CONCAT("T",L$1,"V",$D5,"A",$A5),Vulnerabilities!$G:$G,1,FALSE()),"") | ... P5: =_xlfn.IFNA(VLOOKUP(_xlfn.CONCAT("T",P$1,"V",$D5,"A",$A5),Vulnerabilities!$G:$G,1,FALSE()),"")
A6: 1 | B6: =IF(VLOOKUP($A6,Assets!$A:$C,2,FALSE())=0,"",VLOOKUP($A6,Assets!$A:$C,2,FALSE())) -> Data | C6: =IF(VLOOKUP($A6,Assets!$A:$C,3,FALSE())=0,"",VLOOKUP($A6,Assets!$A:$C,3,FALSE())) -> Client financial records (tax returns, financial statements) | D6: 4 | E6: =_xlfn.IFNA(VLOOKUP(_xlfn.CONCAT("T",E$1,"V",$D6,"A",$A6),Vulnerabilities!$G:$G,1,FALSE()),"") | F6: =_xlfn.IFNA(VLOOKUP(_xlfn.CONCAT("T",F$1,"V",$D6,"A",$A6),Vulnerabilities!$G:$G,1,FALSE()),"") | G6: =_xlfn.IFNA(VLOOKUP(_xlfn.CONCAT("T",G$1,"V",$D6,"A",$A6),Vulnerabilities!$G:$G,1,FALSE()),"") | H6: =_xlfn.IFNA(VLOOKUP(_xlfn.CONCAT("T",H$1,"V",$D6,"A",$A6),Vulnerabilities!$G:$G,1,FALSE()),"") | I6: =_xlfn.IFNA(VLOOKUP(_xlfn.CONCAT("T",I$1,"V",$D6,"A",$A6),Vulnerabilities!$G:$G,1,FALSE()),"") | J6: =_xlfn.IFNA(VLOOKUP(_xlfn.CONCAT("T",J$1,"V",$D6,"A",$A6),Vulnerabilities!$G:$G,1,FALSE()),"") | K6: =_xlfn.IFNA(VLOOKUP(_xlfn.CONCAT("T",K$1,"V",$D6,"A",$A6),Vulnerabilities!$G:$G,1,FALSE()),"") | L6: =_xlfn.IFNA(VLOOKUP(_xlfn.CONCAT("T",L$1,"V",$D6,"A",$A6),Vulnerabilities!$G:$G,1,FALSE()),"") | ... P6: =_xlfn.IFNA(VLOOKUP(_xlfn.CONCAT("T",P$1,"V",$D6,"A",$A6),Vulnerabilities!$G:$G,1,FALSE()),"")
A7: =A3+1 -> 2 | B7: =IF(VLOOKUP($A7,Assets!$A:$C,2,FALSE())=0,"",VLOOKUP($A7,Assets!$A:$C,2,FALSE())) -> Data | C7: =IF(VLOOKUP($A7,Assets!$A:$C,3,FALSE())=0,"",VLOOKUP($A7,Assets!$A:$C,3,FALSE())) -> Client personal information (names, TFNs, addresses) | D7: 1 | E7: =_xlfn.IFNA(VLOOKUP(_xlfn.CONCAT("T",E$1,"V",$D7,"A",$A7),Vulnerabilities!$G:$G,1,FALSE()),"") -> T1V1A2 | F7: =_xlfn.IFNA(VLOOKUP(_xlfn.CONCAT("T",F$1,"V",$D7,"A",$A7),Vulnerabilities!$G:$G,1,FALSE()),"") | G7: =_xlfn.IFNA(VLOOKUP(_xlfn.CONCAT("T",G$1,"V",$D7,"A",$A7),Vulnerabilities!$G:$G,1,FALSE()),"") -> T3V1A2 | H7: =_xlfn.IFNA(VLOOKUP(_xlfn.CONCAT("T",H$1,"V",$D7,"A",$A7),Vulnerabilities!$G:$G,1,FALSE()),"") | I7: =_xlfn.IFNA(VLOOKUP(_xlfn.CONCAT("T",I$1,"V",$D7,"A",$A7),Vulnerabilities!$G:$G,1,FALSE()),"") | J7: =_xlfn.IFNA(VLOOKUP(_xlfn.CONCAT("T",J$1,"V",$D7,"A",$A7),Vulnerabilities!$G:$G,1,FALSE()),"") | K7: =_xlfn.IFNA(VLOOKUP(_xlfn.CONCAT("T",K$1,"V",$D7,"A",$A7),Vulnerabilities!$G:$G,1,FALSE()),"") | L7: =_xlfn.IFNA(VLOOKUP(_xlfn.CONCAT("T",L$1,"V",$D7,"A",$A7),Vulnerabilities!$G:$G,1,FALSE()),"") | ... P7: =_xlfn.IFNA(VLOOKUP(_xlfn.CONCAT("T",P$1,"V",$D7,"A",$A7),Vulnerabilities!$G:$G,1,FALSE()),"")
A8: =A4+1 -> 2 | B8: =IF(VLOOKUP($A8,Assets!$A:$C,2,FALSE())=0,"",VLOOKUP($A8,Assets!$A:$C,2,FALSE())) -> Data | C8: =IF(VLOOKUP($A8,Assets!$A:$C,3,FALSE())=0,"",VLOOKUP($A8,Assets!$A:$C,3,FALSE())) -> Client personal information (names, TFNs, addresses) | D8: 2 | E8: =_xlfn.IFNA(VLOOKUP(_xlfn.CONCAT("T",E$1,"V",$D8,"A",$A8),Vulnerabilities!$G:$G,1,FALSE()),"") | F8: =_xlfn.IFNA(VLOOKUP(_xlfn.CONCAT("T",F$1,"V",$D8,"A",$A8),Vulnerabilities!$G:$G,1,FALSE()),"") | G8: =_xlfn.IFNA(VLOOKUP(_xlfn.CONCAT("T",G$1,"V",$D8,"A",$A8),Vulnerabilities!$G:$G,1,FALSE()),"") | H8: =_xlfn.IFNA(VLOOKUP(_xlfn.CONCAT("T",H$1,"V",$D8,"A",$A8),Vulnerabilities!$G:$G,1,FALSE()),"") | I8: =_xlfn.IFNA(VLOOKUP(_xlfn.CONCAT("T",I$1,"V",$D8,"A",$A8),Vulnerabilities!$G:$G,1,FALSE()),"") | J8: =_xlfn.IFNA(VLOOKUP(_xlfn.CONCAT("T",J$1,"V",$D8,"A",$A8),Vulnerabilities!$G:$G,1,FALSE()),"") | K8: =_xlfn.IFNA(VLOOKUP(_xlfn.CONCAT("T",K$1,"V",$D8,"A",$A8),Vulnerabilities!$G:$G,1,FALSE()),"") | L8: =_xlfn.IFNA(VLOOKUP(_xlfn.CONCAT("T",L$1,"V",$D8,"A",$A8),Vulnerabilities!$G:$G,1,FALSE()),"") | ... P8: =_xlfn.IFNA(VLOOKUP(_xlfn.CONCAT("T",P$1,"V",$D8,"A",$A8),Vulnerabilities!$G:$G,1,FALSE()),"")
A9: =A5+1 -> 2 | B9: =IF(VLOOKUP($A9,Assets!$A:$C,2,FALSE())=0,"",VLOOKUP($A9,Assets!$A:$C,2,FALSE())) -> Data | C9: =IF(VLOOKUP($A9,Assets!$A:$C,3,FALSE())=0,"",VLOOKUP($A9,Assets!$A:$C,3,FALSE())) -> Client personal information (names, TFNs, addresses) | D9: 3 | E9: =_xlfn.IFNA(VLOOKUP(_xlfn.CONCAT("T",E$1,"V",$D9,"A",$A9),Vulnerabilities!$G:$G,1,FALSE()),"") | F9: =_xlfn.IFNA(VLOOKUP(_xlfn.CONCAT("T",F$1,"V",$D9,"A",$A9),Vulnerabilities!$G:$G,1,FALSE()),"") | G9: =_xlfn.IFNA(VLOOKUP(_xlfn.CONCAT("T",G$1,"V",$D9,"A",$A9),Vulnerabilities!$G:$G,1,FALSE()),"") | H9: =_xlfn.IFNA(VLOOKUP(_xlfn.CONCAT("T",H$1,"V",$D9,"A",$A9),Vulnerabilities!$G:$G,1,FALSE()),"") | I9: =_xlfn.IFNA(VLOOKUP(_xlfn.CONCAT("T",I$1,"V",$D9,"A",$A9),Vulnerabilities!$G:$G,1,FALSE()),"") | J9: =_xlfn.IFNA(VLOOKUP(_xlfn.CONCAT("T",J$1,"V",$D9,"A",$A9),Vulnerabilities!$G:$G,1,FALSE()),"") | K9: =_xlfn.IFNA(VLOOKUP(_xlfn.CONCAT("T",K$1,"V",$D9,"A",$A9),Vulnerabilities!$G:$G,1,FALSE()),"") | L9: =_xlfn.IFNA(VLOOKUP(_xlfn.CONCAT("T",L$1,"V",$D9,"A",$A9),Vulnerabilities!$G:$G,1,FALSE()),"") | ... P9: =_xlfn.IFNA(VLOOKUP(_xlfn.CONCAT("T",P$1,"V",$D9,"A",$A9),Vulnerabilities!$G:$G,1,FALSE()),"")
A10: =A6+1 -> 2 | B10: =IF(VLOOKUP($A10,Assets!$A:$C,2,FALSE())=0,"",VLOOKUP($A10,Assets!$A:$C,2,FALSE())) -> Data | C10: =IF(VLOOKUP($A10,Assets!$A:$C,3,FALSE())=0,"",VLOOKUP($A10,Assets!$A:$C,3,FALSE())) -> Client personal information (names, TFNs, addresses) | D10: 4 | E10: =_xlfn.IFNA(VLOOKUP(_xlfn.CONCAT("T",E$1,"V",$D10,"A",$A10),Vulnerabilities!$G:$G,1,FALSE()),"") | F10: =_xlfn.IFNA(VLOOKUP(_xlfn.CONCAT("T",F$1,"V",$D10,"A",$A10),Vulnerabilities!$G:$G,1,FALSE()),"") | G10: =_xlfn.IFNA(VLOOKUP(_xlfn.CONCAT("T",G$1,"V",$D10,"A",$A10),Vulnerabilities!$G:$G,1,FALSE()),"") | H10: =_xlfn.IFNA(VLOOKUP(_xlfn.CONCAT("T",H$1,"V",$D10,"A",$A10),Vulnerabilities!$G:$G,1,FALSE()),"") | I10: =_xlfn.IFNA(VLOOKUP(_xlfn.CONCAT("T",I$1,"V",$D10,"A",$A10),Vulnerabilities!$G:$G,1,FALSE()),"") | J10: =_xlfn.IFNA(VLOOKUP(_xlfn.CONCAT("T",J$1,"V",$D10,"A",$A10),Vulnerabilities!$G:$G,1,FALSE()),"") | K10: =_xlfn.IFNA(VLOOKUP(_xlfn.CONCAT("T",K$1,"V",$D10,"A",$A10),Vulnerabilities!$G:$G,1,FALSE()),"") | L10: =_xlfn.IFNA(VLOOKUP(_xlfn.CONCAT("T",L$1,"V",$D10,"A",$A10),Vulnerabilities!$G:$G,1,FALSE()),"") | ... P10: =_xlfn.IFNA(VLOOKUP(_xlfn.CONCAT("T",P$1,"V",$D10,"A",$A10),Vulnerabilities!$G:$G,1,FALSE()),"")
A11: =A7+1 -> 3 | B11: =IF(VLOOKUP($A11,Assets!$A:$C,2,FALSE())=0,"",VLOOKUP($A11,Assets!$A:$C,2,FALSE())) -> Data | C11: =IF(VLOOKUP($A11,Assets!$A:$C,3,FALSE())=0,"",VLOOKUP($A11,Assets!$A:$C,3,FALSE())) -> Business financial data (accounts, payroll, invoices) | D11: 1 | E11: =_xlfn.IFNA(VLOOKUP(_xlfn.CONCAT("T",E$1,"V",$D11,"A",$A11),Vulnerabilities!$G:$G,1,FALSE()),"") | F11: =_xlfn.IFNA(VLOOKUP(_xlfn.CONCAT("T",F$1,"V",$D11,"A",$A11),Vulnerabilities!$G:$G,1,FALSE()),"") | G11: =_xlfn.IFNA(VLOOKUP(_xlfn.CONCAT("T",G$1,"V",$D11,"A",$A11),Vulnerabilities!$G:$G,1,FALSE()),"") | H11: =_xlfn.IFNA(VLOOKUP(_xlfn.CONCAT("T",H$1,"V",$D11,"A",$A11),Vulnerabilities!$G:$G,1,FALSE()),"") | I11: =_xlfn.IFNA(VLOOKUP(_xlfn.CONCAT("T",I$1,"V",$D11,"A",$A11),Vulnerabilities!$G:$G,1,FALSE()),"") | J11: =_xlfn.IFNA(VLOOKUP(_xlfn.CONCAT("T",J$1,"V",$D11,"A",$A11),Vulnerabilities!$G:$G,1,FALSE()),"") | K11: =_xlfn.IFNA(VLOOKUP(_xlfn.CONCAT("T",K$1,"V",$D11,"A",$A11),Vulnerabilities!$G:$G,1,FALSE()),"") | L11: =_xlfn.IFNA(VLOOKUP(_xlfn.CONCAT("T",L$1,"V",$D11,"A",$A11),Vulnerabilities!$G:$G,1,FALSE()),"") | ... P11: =_xlfn.IFNA(VLOOKUP(_xlfn.CONCAT("T",P$1,"V",$D11,"A",$A11),Vulnerabilities!$G:$G,1,FALSE()),"") -> T12V1A3
A12: =A8+1 -> 3 | B12: =IF(VLOOKUP($A12,Assets!$A:$C,2,FALSE())=0,"",VLOOKUP($A12,Assets!$A:$C,2,FALSE())) -> Data | C12: =IF(VLOOKUP($A12,Assets!$A:$C,3,FALSE())=0,"",VLOOKUP($A12,Assets!$A:$C,3,FALSE())) -> Business financial data (accounts, payroll, invoices) | D12: 2 | E12: =_xlfn.IFNA(VLOOKUP(_xlfn.CONCAT("T",E$1,"V",$D12,"A",$A12),Vulnerabilities!$G:$G,1,FALSE()),"") | F12: =_xlfn.IFNA(VLOOKUP(_xlfn.CONCAT("T",F$1,"V",$D12,"A",$A12),Vulnerabilities!$G:$G,1,FALSE()),"") | G12: =_xlfn.IFNA(VLOOKUP(_xlfn.CONCAT("T",G$1,"V",$D12,"A",$A12),Vulnerabilities!$G:$G,1,FALSE()),"") | H12: =_xlfn.IFNA(VLOOKUP(_xlfn.CONCAT("T",H$1,"V",$D12,"A",$A12),Vulnerabilities!$G:$G,1,FALSE()),"") | I12: =_xlfn.IFNA(VLOOKUP(_xlfn.CONCAT("T",I$1,"V",$D12,"A",$A12),Vulnerabilities!$G:$G,1,FALSE()),"") | J12: =_xlfn.IFNA(VLOOKUP(_xlfn.CONCAT("T",J$1,"V",$D12,"A",$A12),Vulnerabilities!$G:$G,1,FALSE()),"") | K12: =_xlfn.IFNA(VLOOKUP(_xlfn.CONCAT("T",K$1,"V",$D12,"A",$A12),Vulnerabilities!$G:$G,1,FALSE()),"") | L12: =_xlfn.IFNA(VLOOKUP(_xlfn.CONCAT("T",L$1,"V",$D12,"A",$A12),Vulnerabilities!$G:$G,1,FALSE()),"") | ... P12: =_xlfn.IFNA(VLOOKUP(_xlfn.CONCAT("T",P$1,"V",$D12,"A",$A12),Vulnerabilities!$G:$G,1,FALSE()),"")
A13: =A9+1 -> 3 | B13: =IF(VLOOKUP($A13,Assets!$A:$C,2,FALSE())=0,"",VLOOKUP($A13,Assets!$A:$C,2,FALSE())) -> Data | C13: =IF(VLOOKUP($A13,Assets!$A:$C,3,FALSE())=0,"",VLOOKUP($A13,Assets!$A:$C,3,FALSE())) -> Business financial data (accounts, payroll, invoices) | D13: 3 | E13: =_xlfn.IFNA(VLOOKUP(_xlfn.CONCAT("T",E$1,"V",$D13,"A",$A13),Vulnerabilities!$G:$G,1,FALSE()),"") | F13: =_xlfn.IFNA(VLOOKUP(_xlfn.CONCAT("T",F$1,"V",$D13,"A",$A13),Vulnerabilities!$G:$G,1,FALSE()),"") | G13: =_xlfn.IFNA(VLOOKUP(_xlfn.CONCAT("T",G$1,"V",$D13,"A",$A13),Vulnerabilities!$G:$G,1,FALSE()),"") | H13: =_xlfn.IFNA(VLOOKUP(_xlfn.CONCAT("T",H$1,"V",$D13,"A",$A13),Vulnerabilities!$G:$G,1,FALSE()),"") | I13: =_xlfn.IFNA(VLOOKUP(_xlfn.CONCAT("T",I$1,"V",$D13,"A",$A13),Vulnerabilities!$G:$G,1,FALSE()),"") | J13: =_xlfn.IFNA(VLOOKUP(_xlfn.CONCAT("T",J$1,"V",$D13,"A",$A13),Vulnerabilities!$G:$G,1,FALSE()),"") | K13: =_xlfn.IFNA(VLOOKUP(_xlfn.CONCAT("T",K$1,"V",$D13,"A",$A13),Vulnerabilities!$G:$G,1,FALSE()),"") | L13: =_xlfn.IFNA(VLOOKUP(_xlfn.CONCAT("T",L$1,"V",$D13,"A",$A13),Vulnerabilities!$G:$G,1,FALSE()),"") | ... P13: =_xlfn.IFNA(VLOOKUP(_xlfn.CONCAT("T",P$1,"V",$D13,"A",$A13),Vulnerabilities!$G:$G,1,FALSE()),"")
A14: =A10+1 -> 3 | B14: =IF(VLOOKUP($A14,Assets!$A:$C,2,FALSE())=0,"",VLOOKUP($A14,Assets!$A:$C,2,FALSE())) -> Data | C14: =IF(VLOOKUP($A14,Assets!$A:$C,3,FALSE())=0,"",VLOOKUP($A14,Assets!$A:$C,3,FALSE())) -> Business financial data (accounts, payroll, invoices) | D14: 4 | E14: =_xlfn.IFNA(VLOOKUP(_xlfn.CONCAT("T",E$1,"V",$D14,"A",$A14),Vulnerabilities!$G:$G,1,FALSE()),"") | F14: =_xlfn.IFNA(VLOOKUP(_xlfn.CONCAT("T",F$1,"V",$D14,"A",$A14),Vulnerabilities!$G:$G,1,FALSE()),"") | G14: =_xlfn.IFNA(VLOOKUP(_xlfn.CONCAT("T",G$1,"V",$D14,"A",$A14),Vulnerabilities!$G:$G,1,FALSE()),"") | H14: =_xlfn.IFNA(VLOOKUP(_xlfn.CONCAT("T",H$1,"V",$D14,"A",$A14),Vulnerabilities!$G:$G,1,FALSE()),"") | I14: =_xlfn.IFNA(VLOOKUP(_xlfn.CONCAT("T",I$1,"V",$D14,"A",$A14),Vulnerabilities!$G:$G,1,FALSE()),"") | J14: =_xlfn.IFNA(VLOOKUP(_xlfn.CONCAT("T",J$1,"V",$D14,"A",$A14),Vulnerabilities!$G:$G,1,FALSE()),"") | K14: =_xlfn.IFNA(VLOOKUP(_xlfn.CONCAT("T",K$1,"V",$D14,"A",$A14),Vulnerabilities!$G:$G,1,FALSE()),"") | L14: =_xlfn.IFNA(VLOOKUP(_xlfn.CONCAT("T",L$1,"V",$D14,"A",$A14),Vulnerabilities!$G:$G,1,FALSE()),"") | ... P14: =_xlfn.IFNA(VLOOKUP(_xlfn.CONCAT("T",P$1,"V",$D14,"A",$A14),Vulnerabilities!$G:$G,1,FALSE()),"")
A15: =A11+1 -> 4 | B15: =IF(VLOOKUP($A15,Assets!$A:$C,2,FALSE())=0,"",VLOOKUP($A15,Assets!$A:$C,2,FALSE())) -> Data | C15: =IF(VLOOKUP($A15,Assets!$A:$C,3,FALSE())=0,"",VLOOKUP($A15,Assets!$A:$C,3,FALSE())) -> Staff credentials and authentication data | D15: 1 | E15: =_xlfn.IFNA(VLOOKUP(_xlfn.CONCAT("T",E$1,"V",$D15,"A",$A15),Vulnerabilities!$G:$G,1,FALSE()),"") | F15: =_xlfn.IFNA(VLOOKUP(_xlfn.CONCAT("T",F$1,"V",$D15,"A",$A15),Vulnerabilities!$G:$G,1,FALSE()),"") -> T2V1A4 | G15: =_xlfn.IFNA(VLOOKUP(_xlfn.CONCAT("T",G$1,"V",$D15,"A",$A15),Vulnerabilities!$G:$G,1,FALSE()),"") | H15: =_xlfn.IFNA(VLOOKUP(_xlfn.CONCAT("T",H$1,"V",$D15,"A",$A15),Vulnerabilities!$G:$G,1,FALSE()),"") -> T4V1A4 | I15: =_xlfn.IFNA(VLOOKUP(_xlfn.CONCAT("T",I$1,"V",$D15,"A",$A15),Vulnerabilities!$G:$G,1,FALSE()),"") | J15: =_xlfn.IFNA(VLOOKUP(_xlfn.CONCAT("T",J$1,"V",$D15,"A",$A15),Vulnerabilities!$G:$G,1,FALSE()),"") | K15: =_xlfn.IFNA(VLOOKUP(_xlfn.CONCAT("T",K$1,"V",$D15,"A",$A15),Vulnerabilities!$G:$G,1,FALSE()),"") | L15: =_xlfn.IFNA(VLOOKUP(_xlfn.CONCAT("T",L$1,"V",$D15,"A",$A15),Vulnerabilities!$G:$G,1,FALSE()),"") | ... P15: =_xlfn.IFNA(VLOOKUP(_xlfn.CONCAT("T",P$1,"V",$D15,"A",$A15),Vulnerabilities!$G:$G,1,FALSE()),"")
A16: =A12+1 -> 4 | B16: =IF(VLOOKUP($A16,Assets!$A:$C,2,FALSE())=0,"",VLOOKUP($A16,Assets!$A:$C,2,FALSE())) -> Data | C16: =IF(VLOOKUP($A16,Assets!$A:$C,3,FALSE())=0,"",VLOOKUP($A16,Assets!$A:$C,3,FALSE())) -> Staff credentials and authentication data | D16: 2 | E16: =_xlfn.IFNA(VLOOKUP(_xlfn.CONCAT("T",E$1,"V",$D16,"A",$A16),Vulnerabilities!$G:$G,1,FALSE()),"") | F16: =_xlfn.IFNA(VLOOKUP(_xlfn.CONCAT("T",F$1,"V",$D16,"A",$A16),Vulnerabilities!$G:$G,1,FALSE()),"") | G16: =_xlfn.IFNA(VLOOKUP(_xlfn.CONCAT("T",G$1,"V",$D16,"A",$A16),Vulnerabilities!$G:$G,1,FALSE()),"") | H16: =_xlfn.IFNA(VLOOKUP(_xlfn.CONCAT("T",H$1,"V",$D16,"A",$A16),Vulnerabilities!$G:$G,1,FALSE()),"") | I16: =_xlfn.IFNA(VLOOKUP(_xlfn.CONCAT("T",I$1,"V",$D16,"A",$A16),Vulnerabilities!$G:$G,1,FALSE()),"") | J16: =_xlfn.IFNA(VLOOKUP(_xlfn.CONCAT("T",J$1,"V",$D16,"A",$A16),Vulnerabilities!$G:$G,1,FALSE()),"") | K16: =_xlfn.IFNA(VLOOKUP(_xlfn.CONCAT("T",K$1,"V",$D16,"A",$A16),Vulnerabilities!$G:$G,1,FALSE()),"") | L16: =_xlfn.IFNA(VLOOKUP(_xlfn.CONCAT("T",L$1,"V",$D16,"A",$A16),Vulnerabilities!$G:$G,1,FALSE()),"") | ... P16: =_xlfn.IFNA(VLOOKUP(_xlfn.CONCAT("T",P$1,"V",$D16,"A",$A16),Vulnerabilities!$G:$G,1,FALSE()),"")
A17: =A13+1 -> 4 | B17: =IF(VLOOKUP($A17,Assets!$A:$C,2,FALSE())=0,"",VLOOKUP($A17,Assets!$A:$C,2,FALSE())) -> Data | C17: =IF(VLOOKUP($A17,Assets!$A:$C,3,FALSE())=0,"",VLOOKUP($A17,Assets!$A:$C,3,FALSE())) -> Staff credentials and authentication data | D17: 3 | E17: =_xlfn.IFNA(VLOOKUP(_xlfn.CONCAT("T",E$1,"V",$D17,"A",$A17),Vulnerabilities!$G:$G,1,FALSE()),"") | F17: =_xlfn.IFNA(VLOOKUP(_xlfn.CONCAT("T",F$1,"V",$D17,"A",$A17),Vulnerabilities!$G:$G,1,FALSE()),"") | G17: =_xlfn.IFNA(VLOOKUP(_xlfn.CONCAT("T",G$1,"V",$D17,"A",$A17),Vulnerabilities!$G:$G,1,FALSE()),"") | H17: =_xlfn.IFNA(VLOOKUP(_xlfn.CONCAT("T",H$1,"V",$D17,"A",$A17),Vulnerabilities!$G:$G,1,FALSE()),"") | I17: =_xlfn.IFNA(VLOOKUP(_xlfn.CONCAT("T",I$1,"V",$D17,"A",$A17),Vulnerabilities!$G:$G,1,FALSE()),"") | J17: =_xlfn.IFNA(VLOOKUP(_xlfn.CONCAT("T",J$1,"V",$D17,"A",$A17),Vulnerabilities!$G:$G,1,FALSE()),"") | K17: =_xlfn.IFNA(VLOOKUP(_xlfn.CONCAT("T",K$1,"V",$D17,"A",$A17),Vulnerabilities!$G:$G,1,FALSE()),"") | L17: =_xlfn.IFNA(VLOOKUP(_xlfn.CONCAT("T",L$1,"V",$D17,"A",$A17),Vulnerabilities!$G:$G,1,FALSE()),"") | ... P17: =_xlfn.IFNA(VLOOKUP(_xlfn.CONCAT("T",P$1,"V",$D17,"A",$A17),Vulnerabilities!$G:$G,1,FALSE()),"")
A18: =A14+1 -> 4 | B18: =IF(VLOOKUP($A18,Assets!$A:$C,2,FALSE())=0,"",VLOOKUP($A18,Assets!$A:$C,2,FALSE())) -> Data | C18: =IF(VLOOKUP($A18,Assets!$A:$C,3,FALSE())=0,"",VLOOKUP($A18,Assets!$A:$C,3,FALSE())) -> Staff credentials and authentication data | D18: 4 | E18: =_xlfn.IFNA(VLOOKUP(_xlfn.CONCAT("T",E$1,"V",$D18,"A",$A18),Vulnerabilities!$G:$G,1,FALSE()),"") | F18: =_xlfn.IFNA(VLOOKUP(_xlfn.CONCAT("T",F$1,"V",$D18,"A",$A18),Vulnerabilities!$G:$G,1,FALSE()),"") | G18: =_xlfn.IFNA(VLOOKUP(_xlfn.CONCAT("T",G$1,"V",$D18,"A",$A18),Vulnerabilities!$G:$G,1,FALSE()),"") | H18: =_xlfn.IFNA(VLOOKUP(_xlfn.CONCAT("T",H$1,"V",$D18,"A",$A18),Vulnerabilities!$G:$G,1,FALSE()),"") | I18: =_xlfn.IFNA(VLOOKUP(_xlfn.CONCAT("T",I$1,"V",$D18,"A",$A18),Vulnerabilities!$G:$G,1,FALSE()),"") | J18: =_xlfn.IFNA(VLOOKUP(_xlfn.CONCAT("T",J$1,"V",$D18,"A",$A18),Vulnerabilities!$G:$G,1,FALSE()),"") | K18: =_xlfn.IFNA(VLOOKUP(_xlfn.CONCAT("T",K$1,"V",$D18,"A",$A18),Vulnerabilities!$G:$G,1,FALSE()),"") | L18: =_xlfn.IFNA(VLOOKUP(_xlfn.CONCAT("T",L$1,"V",$D18,"A",$A18),Vulnerabilities!$G:$G,1,FALSE()),"") | ... P18: =_xlfn.IFNA(VLOOKUP(_xlfn.CONCAT("T",P$1,"V",$D18,"A",$A18),Vulnerabilities!$G:$G,1,FALSE()),"")
... A58: =A54+1 -> 14 | B58: =IF(VLOOKUP($A58,Assets!$A:$C,2,FALSE())=0,"",VLOOKUP($A58,Assets!$A:$C,2,FALSE())) -> People | C58: =IF(VLOOKUP($A58,Assets!$A:$C,3,FALSE())=0,"",VLOOKUP($A58,Assets!$A:$C,3,FALSE())) -> Accountants (x5) | D58: 4 | E58: =_xlfn.IFNA(VLOOKUP(_xlfn.CONCAT("T",E$1,"V",$D58,"A",$A58),Vulnerabilities!$G:$G,1,FALSE()),"") | F58: =_xlfn.IFNA(VLOOKUP(_xlfn.CONCAT("T",F$1,"V",$D58,"A",$A58),Vulnerabilities!$G:$G,1,FALSE()),"") | G58: =_xlfn.IFNA(VLOOKUP(_xlfn.CONCAT("T",G$1,"V",$D58,"A",$A58),Vulnerabilities!$G:$G,1,FALSE()),"") | H58: =_xlfn.IFNA(VLOOKUP(_xlfn.CONCAT("T",H$1,"V",$D58,"A",$A58),Vulnerabilities!$G:$G,1,FALSE()),"") | I58: =_xlfn.IFNA(VLOOKUP(_xlfn.CONCAT("T",I$1,"V",$D58,"A",$A58),Vulnerabilities!$G:$G,1,FALSE()),"") | J58: =_xlfn.IFNA(VLOOKUP(_xlfn.CONCAT("T",J$1,"V",$D58,"A",$A58),Vulnerabilities!$G:$G,1,FALSE()),"") | K58: =_xlfn.IFNA(VLOOKUP(_xlfn.CONCAT("T",K$1,"V",$D58,"A",$A58),Vulnerabilities!$G:$G,1,FALSE()),"") | L58: =_xlfn.IFNA(VLOOKUP(_xlfn.CONCAT("T",L$1,"V",$D58,"A",$A58),Vulnerabilities!$G:$G,1,FALSE()),"") | ... P58: =_xlfn.IFNA(VLOOKUP(_xlfn.CONCAT("T",P$1,"V",$D58,"A",$A58),Vulnerabilities!$G:$G,1,FALSE()),"")

Sheet AssetTypes
A1: AssetTypes
A2: Data
A3: Hardware
A4: Software
A5: Network
A6: People
A7: Processes

Sheet RiskValues
A1: Likelihood | B1: Impact | C1: Combined | D1: Risk
A2: Very High | B2: Very Low | C2: =_xlfn.CONCAT(A2,"|",B2) -> Very High|Very Low | D2: Very Low
A3: High | B3: Very Low | C3: =_xlfn.CONCAT(A3,"|",B3) -> High|Very Low | D3: Very Low
A4: Moderate | B4: Very Low | C4: =_xlfn.CONCAT(A4,"|",B4) -> Moderate|Very Low | D4: Very Low
A5: Low | B5: Very Low | C5: =_xlfn.CONCAT(A5,"|",B5) -> Low|Very Low | D5: Very Low
A6: Very Low | B6: Very Low | C6: =_xlfn.CONCAT(A6,"|",B6) -> Very Low|Very Low | D6: Very Low
A7: Very High | B7: Low | C7: =_xlfn.CONCAT(A7,"|",B7) -> Very High|Low | D7: Low
A8: High | B8: Low | C8: =_xlfn.CONCAT(A8,"|",B8) -> High|Low | D8: Low
A9: Moderate | B9: Low | C9: =_xlfn.CONCAT(A9,"|",B9) -> Moderate|Low | D9: Low
A10: Low | B10: Low | C10: =_xlfn.CONCAT(A10,"|",B10) -> Low|Low | D10: Low
A11: Very Low | B11: Low | C11: =_xlfn.CONCAT(A11,"|",B11) -> Very Low|Low | D11: Very Low
A12: Very High | B12: Moderate | C12: =_xlfn.CONCAT(A12,"|",B12) -> Very High|Moderate | D12: Moderate
A13: High | B13: Moderate | C13: =_xlfn.CONCAT(A13,"|",B13) -> High|Moderate | D13: Moderate
... A26: Very Low | B26: Very High | C26: =_xlfn.CONCAT(A26,"|",B26) -> Very Low|Very High | D26: Low

Sheet InfoSecThreats
A1: ThreatNum | B1: Threat | C1: Description
A2: 1 | B2: People errors | C2: E.g. social engineering, phishing & server misconfigurations
A3: 2 | B3: Software attacks | C3: Backdoor, DoS, Interceptions (MITM, sniffing, DNS poisoning, session hijacking, spoofing), malware
A4: 3 | B4: Information extortion | C4: Ransomware, blackmail & info disclosure
A5: 4 | B5: Espionage and trespass | C5: Unauthorised access, e.g. via password attacks
A6: 5 | B6: Theft | C6: Illegal confiscation of assets
A7: 6 | B7: Technological obsolescence | C7: Outdated tech
A8: 7 | B8: Forces of nature | C8: E.g. cyclone, fire, flood & lightening
A9: 8 | B9: Technical hardware failures or errors | C9: E.g. leaky capacitors, drive failure
A10: 9 | B10: Technical software failures or errors | C10: Bugs, code performance issues & loopholes
A11: 10 | B11: Changing quality of services | C11: E.g. blackout, brownout, Spike, NBN outage
A12: 11 | B12: Sabotage and vandalism | C12: Destruction of assets
A13: 12 | B13: IP compromises | C13: Piracy & copyright infringement
